{"chunk_definitions":[{"chunk_id":"cuh8pxkcl1923","chunk_label":"unnamed-chunk-1","document_id":"67AF326E","expansion_state":0,"options":{"echo":false,"engine":"r","label":"unnamed-chunk-9","message":false,"warning":false},"row":5,"row_count":1,"visible":true},{"chunk_id":"cmcgjrtd3c4pu","chunk_label":"read","document_id":"67AF326E","expansion_state":0,"options":{"engine":"r","label":"read"},"row":11,"row_count":1,"visible":true},{"chunk_id":"cci313l4jqmae","chunk_label":"unnamed-chunk-2","document_id":"67AF326E","expansion_state":0,"options":{},"row":18,"row_count":1,"visible":true},{"chunk_id":"c9v712ok5mkmn","chunk_label":"unnamed-chunk-3","document_id":"67AF326E","expansion_state":0,"options":{},"row":23,"row_count":1,"visible":true},{"chunk_id":"cajjn7auq0g4t","chunk_label":"unnamed-chunk-4","document_id":"67AF326E","expansion_state":0,"options":{},"row":28,"row_count":1,"visible":true}],"doc_write_time":1554341192}